encrypted_text_field/__init__.py
encrypted_text_field/forms.py
encrypted_text_field/models.py
encrypted_text_field/management/__init__.py
encrypted_text_field/management/commands/__init__.py
encrypted_text_field/management/commands/generate_encryption_key.py
encrypted_text_field-0.1.1.dist-info/LICENSE
encrypted_text_field-0.1.1.dist-info/METADATA
encrypted_text_field-0.1.1.dist-info/WHEEL
encrypted_text_field-0.1.1.dist-info/top_level.txt
encrypted_text_field-0.1.1.dist-info/RECORD
