Metadata-Version: 2.1
Name: encrypted-text-field
Version: 0.1.1
Summary: A Django app providing a custom model field for storing sensitive information.
Home-page: https://github.com/codingcowde/encrypted_text_field
Author: codingcow
Author-email: etf@codingcow.de
License: MIT License
Platform: UNKNOWN
Classifier: Development Status :: 5 - Production/Stable
Classifier: Environment :: Web Environment
Classifier: Framework :: Django
Classifier: Framework :: Django :: 3.2
Classifier: Intended Audience :: Developers
Classifier: License :: OSI Approved :: MIT License
Classifier: Operating System :: OS Independent
Classifier: Programming Language :: Python
Classifier: Programming Language :: Python :: 3.9
Classifier: Programming Language :: Python :: 3.10
Classifier: Programming Language :: Python :: 3.12
Classifier: Topic :: Internet :: WWW/HTTP
Classifier: Topic :: Internet :: WWW/HTTP :: Dynamic Content
License-File: LICENSE
Requires-Dist: Django (>=3.2)
Requires-Dist: cryptography
